django_jwt/__init__.py
django_jwt/config.py
django_jwt/exceptions.py
django_jwt/middleware.py
django_jwt/pkce.py
django_jwt/roles.py
django_jwt/settings.py
django_jwt/urls.py
django_jwt/user.py
django_jwt/utils.py
django_jwt/views.py
django_jwt/templates/django-jwt-index.html
django_jwt/templates/admin/login.html
tests/__init__.py
tests/models.py
tests/test.py
tests/urls.py
dj_jwt_auth-1.9.6.dist-info/METADATA
dj_jwt_auth-1.9.6.dist-info/WHEEL
dj_jwt_auth-1.9.6.dist-info/top_level.txt
dj_jwt_auth-1.9.6.dist-info/RECORD
