Metadata-Version: 2.1
Name: dj-jwt-auth
Version: 1.9.6
Summary: A Django package for JSON Web Token validation and verification. Using PyJWT.
Home-page: https://www.example.com/
Author: Konstantin Seleznev
Author-email: k.seleznev@elsevier.com
License: MIT
Classifier: Environment :: Web Environment
Classifier: Framework :: Django
Classifier: Intended Audience :: Developers
Classifier: License :: OSI Approved :: MIT License
Classifier: Operating System :: OS Independent
Classifier: Programming Language :: Python
Classifier: Programming Language :: Python :: 3
Classifier: Programming Language :: Python :: 3 :: Only
Classifier: Programming Language :: Python :: 3.9
Classifier: Programming Language :: Python :: 3.10
Classifier: Programming Language :: Python :: 3.11
Classifier: Programming Language :: Python :: 3.12
Classifier: Topic :: Internet :: WWW/HTTP
Classifier: Topic :: Internet :: WWW/HTTP :: Dynamic Content
Requires-Python: >=3.8
Requires-Dist: Django>=3.0
Requires-Dist: pyjwt>=2.5.0
Requires-Dist: requests>=2.28.1
Requires-Dist: cryptography>=36.0.2
